[
	{
		"Numero" : 1,
		"Nombre_Completo" : "ESMERLIN AQUINO",
		"Posicion" : "3B",
		"Total_Turnos_Juego1" : 228,
		"Total_H1_Juego1" : 36,
		"Total_H2_Juego1" : 24,
		"Total_H3_Juego1" : 0,
		"Total_H4_Juego1" : 12,
		"Total_BB_Juego1" : 0,
		"Total_K_Juego1" : 0,
		"Total_Remolcadas_Juego1" : 12,
		"Total_Anotadas_Juego1" : 12,
		"Total_Turnos_Juego2" : 196,
		"Total_H1_Juego2" : 56,
		"Total_H2_Juego2" : 42,
		"Total_H3_Juego2" : 14,
		"Total_H4_Juego2" : 0,
		"Total_BB_Juego2" : 14,
		"Total_K_Juego2" : 0,
		"Total_Remolcadas_Juego2" : 14,
		"Total_Anotadas_Juego2" : 28,
		"Total_Innings_Lanzados" : 336.0,
		"Total_Ponches_Pitcher" : 42,
		"Total_BB_Pitcher" : 252
	},
	{
		"Numero" : 2,
		"Nombre_Completo" : "LA FEDE CHICHI",
		"Posicion" : "RF",
		"Total_Turnos_Juego1" : 14,
		"Total_H1_Juego1" : 2,
		"Total_H2_Juego1" : 0,
		"Total_H3_Juego1" : 0,
		"Total_H4_Juego1" : 0,
		"Total_BB_Juego1" : 0,
		"Total_K_Juego1" : 2,
		"Total_Remolcadas_Juego1" : 2,
		"Total_Anotadas_Juego1" : 0,
		"Total_Turnos_Juego2" : 12,
		"Total_H1_Juego2" : 3,
		"Total_H2_Juego2" : 0,
		"Total_H3_Juego2" : 3,
		"Total_H4_Juego2" : 0,
		"Total_BB_Juego2" : 0,
		"Total_K_Juego2" : 0,
		"Total_Remolcadas_Juego2" : 0,
		"Total_Anotadas_Juego2" : 0,
		"Total_Innings_Lanzados" : 0.0,
		"Total_Ponches_Pitcher" : 0,
		"Total_BB_Pitcher" : 0
	},
	{
		"Numero" : 3,
		"Nombre_Completo" : "JOSELUIS HENRIQUEZ",
		"Posicion" : "CF",
		"Total_Turnos_Juego1" : 161,
		"Total_H1_Juego1" : 56,
		"Total_H2_Juego1" : 14,
		"Total_H3_Juego1" : 14,
		"Total_H4_Juego1" : 0,
		"Total_BB_Juego1" : 0,
		"Total_K_Juego1" : 14,
		"Total_Remolcadas_Juego1" : 7,
		"Total_Anotadas_Juego1" : 21,
		"Total_Turnos_Juego2" : 112,
		"Total_H1_Juego2" : 24,
		"Total_H2_Juego2" : 24,
		"Total_H3_Juego2" : 16,
		"Total_H4_Juego2" : 0,
		"Total_BB_Juego2" : 0,
		"Total_K_Juego2" : 8,
		"Total_Remolcadas_Juego2" : 0,
		"Total_Anotadas_Juego2" : 24,
		"Total_Innings_Lanzados" : 0.0,
		"Total_Ponches_Pitcher" : 0,
		"Total_BB_Pitcher" : 0
	},
	{
		"Numero" : 4,
		"Nombre_Completo" : "COCHI VASQUEZ",
		"Posicion" : "P",
		"Total_Turnos_Juego1" : 42,
		"Total_H1_Juego1" : 12,
		"Total_H2_Juego1" : 0,
		"Total_H3_Juego1" : 0,
		"Total_H4_Juego1" : 0,
		"Total_BB_Juego1" : 0,
		"Total_K_Juego1" : 0,
		"Total_Remolcadas_Juego1" : 0,
		"Total_Anotadas_Juego1" : 0,
		"Total_Turnos_Juego2" : 45,
		"Total_H1_Juego2" : 27,
		"Total_H2_Juego2" : 0,
		"Total_H3_Juego2" : 0,
		"Total_H4_Juego2" : 0,
		"Total_BB_Juego2" : 9,
		"Total_K_Juego2" : 0,
		"Total_Remolcadas_Juego2" : 0,
		"Total_Anotadas_Juego2" : 0,
		"Total_Innings_Lanzados" : 150.0,
		"Total_Ponches_Pitcher" : 30,
		"Total_BB_Pitcher" : 24
	},
	{
		"Numero" : 5,
		"Nombre_Completo" : "FRISSO WILSON",
		"Posicion" : "C",
		"Total_Turnos_Juego1" : 133,
		"Total_H1_Juego1" : 7,
		"Total_H2_Juego1" : 28,
		"Total_H3_Juego1" : 7,
		"Total_H4_Juego1" : 0,
		"Total_BB_Juego1" : 28,
		"Total_K_Juego1" : 7,
		"Total_Remolcadas_Juego1" : 0,
		"Total_Anotadas_Juego1" : 0,
		"Total_Turnos_Juego2" : 91,
		"Total_H1_Juego2" : 7,
		"Total_H2_Juego2" : 7,
		"Total_H3_Juego2" : 0,
		"Total_H4_Juego2" : 14,
		"Total_BB_Juego2" : 14,
		"Total_K_Juego2" : 7,
		"Total_Remolcadas_Juego2" : 0,
		"Total_Anotadas_Juego2" : 7,
		"Total_Innings_Lanzados" : 0.0,
		"Total_Ponches_Pitcher" : 0,
		"Total_BB_Pitcher" : 0
	},
	{
		"Numero" : 6,
		"Nombre_Completo" : "NAO FIGUEROA",
		"Posicion" : "RF",
		"Total_Turnos_Juego1" : 36,
		"Total_H1_Juego1" : 20,
		"Total_H2_Juego1" : 0,
		"Total_H3_Juego1" : 0,
		"Total_H4_Juego1" : 0,
		"Total_BB_Juego1" : 4,
		"Total_K_Juego1" : 4,
		"Total_Remolcadas_Juego1" : 0,
		"Total_Anotadas_Juego1" : 0,
		"Total_Turnos_Juego2" : 32,
		"Total_H1_Juego2" : 8,
		"Total_H2_Juego2" : 4,
		"Total_H3_Juego2" : 4,
		"Total_H4_Juego2" : 0,
		"Total_BB_Juego2" : 0,
		"Total_K_Juego2" : 0,
		"Total_Remolcadas_Juego2" : 0,
		"Total_Anotadas_Juego2" : 0,
		"Total_Innings_Lanzados" : 0.0,
		"Total_Ponches_Pitcher" : 0,
		"Total_BB_Pitcher" : 0
	},
	{
		"Numero" : 7,
		"Nombre_Completo" : "CHULO PUJOLS",
		"Posicion" : "1B",
		"Total_Turnos_Juego1" : 85,
		"Total_H1_Juego1" : 15,
		"Total_H2_Juego1" : 20,
		"Total_H3_Juego1" : 0,
		"Total_H4_Juego1" : 0,
		"Total_BB_Juego1" : 5,
		"Total_K_Juego1" : 0,
		"Total_Remolcadas_Juego1" : 0,
		"Total_Anotadas_Juego1" : 5,
		"Total_Turnos_Juego2" : 54,
		"Total_H1_Juego2" : 6,
		"Total_H2_Juego2" : 12,
		"Total_H3_Juego2" : 6,
		"Total_H4_Juego2" : 0,
		"Total_BB_Juego2" : 0,
		"Total_K_Juego2" : 6,
		"Total_Remolcadas_Juego2" : 6,
		"Total_Anotadas_Juego2" : 6,
		"Total_Innings_Lanzados" : 0.0,
		"Total_Ponches_Pitcher" : 0,
		"Total_BB_Pitcher" : 0
	},
	{
		"Numero" : 12,
		"Nombre_Completo" : "MIGUEL FIGUEROA",
		"Posicion" : "P",
		"Total_Turnos_Juego1" : 5,
		"Total_H1_Juego1" : 2,
		"Total_H2_Juego1" : 0,
		"Total_H3_Juego1" : 0,
		"Total_H4_Juego1" : 0,
		"Total_BB_Juego1" : 0,
		"Total_K_Juego1" : 1,
		"Total_Remolcadas_Juego1" : 0,
		"Total_Anotadas_Juego1" : 0,
		"Total_Turnos_Juego2" : 4,
		"Total_H1_Juego2" : 0,
		"Total_H2_Juego2" : 2,
		"Total_H3_Juego2" : 0,
		"Total_H4_Juego2" : 0,
		"Total_BB_Juego2" : 2,
		"Total_K_Juego2" : 0,
		"Total_Remolcadas_Juego2" : 0,
		"Total_Anotadas_Juego2" : 0,
		"Total_Innings_Lanzados" : 4.0,
		"Total_Ponches_Pitcher" : 0,
		"Total_BB_Pitcher" : 0
	},
	{
		"Numero" : 13,
		"Nombre_Completo" : "YERIFEN JEREZ",
		"Posicion" : "SS",
		"Total_Turnos_Juego1" : 70,
		"Total_H1_Juego1" : 30,
		"Total_H2_Juego1" : 0,
		"Total_H3_Juego1" : 5,
		"Total_H4_Juego1" : 5,
		"Total_BB_Juego1" : 5,
		"Total_K_Juego1" : 0,
		"Total_Remolcadas_Juego1" : 30,
		"Total_Anotadas_Juego1" : 5,
		"Total_Turnos_Juego2" : 78,
		"Total_H1_Juego2" : 18,
		"Total_H2_Juego2" : 12,
		"Total_H3_Juego2" : 0,
		"Total_H4_Juego2" : 6,
		"Total_BB_Juego2" : 0,
		"Total_K_Juego2" : 12,
		"Total_Remolcadas_Juego2" : 6,
		"Total_Anotadas_Juego2" : 6,
		"Total_Innings_Lanzados" : 0.0,
		"Total_Ponches_Pitcher" : 0,
		"Total_BB_Pitcher" : 0
	},
	{
		"Numero" : 15,
		"Nombre_Completo" : "MODESTO DE LA ROSA",
		"Posicion" : "2B",
		"Total_Turnos_Juego1" : 10,
		"Total_H1_Juego1" : 4,
		"Total_H2_Juego1" : 0,
		"Total_H3_Juego1" : 0,
		"Total_H4_Juego1" : 0,
		"Total_BB_Juego1" : 0,
		"Total_K_Juego1" : 0,
		"Total_Remolcadas_Juego1" : 2,
		"Total_Anotadas_Juego1" : 0,
		"Total_Turnos_Juego2" : 8,
		"Total_H1_Juego2" : 4,
		"Total_H2_Juego2" : 0,
		"Total_H3_Juego2" : 0,
		"Total_H4_Juego2" : 0,
		"Total_BB_Juego2" : 0,
		"Total_K_Juego2" : 0,
		"Total_Remolcadas_Juego2" : 4,
		"Total_Anotadas_Juego2" : 2,
		"Total_Innings_Lanzados" : 0.0,
		"Total_Ponches_Pitcher" : 0,
		"Total_BB_Pitcher" : 0
	},
	{
		"Numero" : 18,
		"Nombre_Completo" : "JUNIOR BOBOLO",
		"Posicion" : "LF",
		"Total_Turnos_Juego1" : 6,
		"Total_H1_Juego1" : 2,
		"Total_H2_Juego1" : 0,
		"Total_H3_Juego1" : 0,
		"Total_H4_Juego1" : 0,
		"Total_BB_Juego1" : 1,
		"Total_K_Juego1" : 0,
		"Total_Remolcadas_Juego1" : 0,
		"Total_Anotadas_Juego1" : 0,
		"Total_Turnos_Juego2" : 4,
		"Total_H1_Juego2" : 0,
		"Total_H2_Juego2" : 0,
		"Total_H3_Juego2" : 0,
		"Total_H4_Juego2" : 0,
		"Total_BB_Juego2" : 0,
		"Total_K_Juego2" : 0,
		"Total_Remolcadas_Juego2" : 0,
		"Total_Anotadas_Juego2" : 0,
		"Total_Innings_Lanzados" : 0.0,
		"Total_Ponches_Pitcher" : 0,
		"Total_BB_Pitcher" : 0
	},
	{
		"Numero" : 20,
		"Nombre_Completo" : "ERIC BENCOSME",
		"Posicion" : "LF",
		"Total_Turnos_Juego1" : 84,
		"Total_H1_Juego1" : 24,
		"Total_H2_Juego1" : 6,
		"Total_H3_Juego1" : 0,
		"Total_H4_Juego1" : 0,
		"Total_BB_Juego1" : 12,
		"Total_K_Juego1" : 6,
		"Total_Remolcadas_Juego1" : 0,
		"Total_Anotadas_Juego1" : 0,
		"Total_Turnos_Juego2" : 65,
		"Total_H1_Juego2" : 5,
		"Total_H2_Juego2" : 15,
		"Total_H3_Juego2" : 0,
		"Total_H4_Juego2" : 5,
		"Total_BB_Juego2" : 10,
		"Total_K_Juego2" : 10,
		"Total_Remolcadas_Juego2" : 0,
		"Total_Anotadas_Juego2" : 5,
		"Total_Innings_Lanzados" : 0.0,
		"Total_Ponches_Pitcher" : 0,
		"Total_BB_Pitcher" : 0
	},
	{
		"Numero" : 25,
		"Nombre_Completo" : "Ángel Grullón",
		"Posicion" : "2B",
		"Total_Turnos_Juego1" : 85,
		"Total_H1_Juego1" : 15,
		"Total_H2_Juego1" : 10,
		"Total_H3_Juego1" : 0,
		"Total_H4_Juego1" : 15,
		"Total_BB_Juego1" : 5,
		"Total_K_Juego1" : 0,
		"Total_Remolcadas_Juego1" : 5,
		"Total_Anotadas_Juego1" : 5,
		"Total_Turnos_Juego2" : 66,
		"Total_H1_Juego2" : 6,
		"Total_H2_Juego2" : 0,
		"Total_H3_Juego2" : 6,
		"Total_H4_Juego2" : 12,
		"Total_BB_Juego2" : 6,
		"Total_K_Juego2" : 12,
		"Total_Remolcadas_Juego2" : 6,
		"Total_Anotadas_Juego2" : 0,
		"Total_Innings_Lanzados" : 0.0,
		"Total_Ponches_Pitcher" : 0,
		"Total_BB_Pitcher" : 0
	},
	{
		"Numero" : 26,
		"Nombre_Completo" : "ANGEL MOREL",
		"Posicion" : "3B",
		"Total_Turnos_Juego1" : 7,
		"Total_H1_Juego1" : 0,
		"Total_H2_Juego1" : 0,
		"Total_H3_Juego1" : 0,
		"Total_H4_Juego1" : 0,
		"Total_BB_Juego1" : 2,
		"Total_K_Juego1" : 3,
		"Total_Remolcadas_Juego1" : 0,
		"Total_Anotadas_Juego1" : 0,
		"Total_Turnos_Juego2" : 4,
		"Total_H1_Juego2" : 0,
		"Total_H2_Juego2" : 2,
		"Total_H3_Juego2" : 0,
		"Total_H4_Juego2" : 0,
		"Total_BB_Juego2" : 0,
		"Total_K_Juego2" : 0,
		"Total_Remolcadas_Juego2" : 0,
		"Total_Anotadas_Juego2" : 0,
		"Total_Innings_Lanzados" : 0.0,
		"Total_Ponches_Pitcher" : 0,
		"Total_BB_Pitcher" : 0
	},
	{
		"Numero" : 27,
		"Nombre_Completo" : "ANEURIS SIMBA",
		"Posicion" : "C",
		"Total_Turnos_Juego1" : 0,
		"Total_H1_Juego1" : 0,
		"Total_H2_Juego1" : 0,
		"Total_H3_Juego1" : 0,
		"Total_H4_Juego1" : 0,
		"Total_BB_Juego1" : 0,
		"Total_K_Juego1" : 0,
		"Total_Remolcadas_Juego1" : 0,
		"Total_Anotadas_Juego1" : 0,
		"Total_Turnos_Juego2" : 0,
		"Total_H1_Juego2" : 0,
		"Total_H2_Juego2" : 0,
		"Total_H3_Juego2" : 0,
		"Total_H4_Juego2" : 0,
		"Total_BB_Juego2" : 0,
		"Total_K_Juego2" : 0,
		"Total_Remolcadas_Juego2" : 0,
		"Total_Anotadas_Juego2" : 0,
		"Total_Innings_Lanzados" : 0.0,
		"Total_Ponches_Pitcher" : 0,
		"Total_BB_Pitcher" : 0
	},
	{
		"Numero" : 28,
		"Nombre_Completo" : "ALAMO CABRERA",
		"Posicion" : "3B",
		"Total_Turnos_Juego1" : 0,
		"Total_H1_Juego1" : 0,
		"Total_H2_Juego1" : 0,
		"Total_H3_Juego1" : 0,
		"Total_H4_Juego1" : 0,
		"Total_BB_Juego1" : 0,
		"Total_K_Juego1" : 0,
		"Total_Remolcadas_Juego1" : 0,
		"Total_Anotadas_Juego1" : 0,
		"Total_Turnos_Juego2" : 0,
		"Total_H1_Juego2" : 0,
		"Total_H2_Juego2" : 0,
		"Total_H3_Juego2" : 0,
		"Total_H4_Juego2" : 0,
		"Total_BB_Juego2" : 0,
		"Total_K_Juego2" : 0,
		"Total_Remolcadas_Juego2" : 0,
		"Total_Anotadas_Juego2" : 0,
		"Total_Innings_Lanzados" : 0.0,
		"Total_Ponches_Pitcher" : 0,
		"Total_BB_Pitcher" : 0
	},
	{
		"Numero" : 30,
		"Nombre_Completo" : "LUIS FELIPE HEREDIA",
		"Posicion" : "LF",
		"Total_Turnos_Juego1" : 10,
		"Total_H1_Juego1" : 2,
		"Total_H2_Juego1" : 1,
		"Total_H3_Juego1" : 0,
		"Total_H4_Juego1" : 1,
		"Total_BB_Juego1" : 3,
		"Total_K_Juego1" : 0,
		"Total_Remolcadas_Juego1" : 0,
		"Total_Anotadas_Juego1" : 2,
		"Total_Turnos_Juego2" : 6,
		"Total_H1_Juego2" : 3,
		"Total_H2_Juego2" : 0,
		"Total_H3_Juego2" : 3,
		"Total_H4_Juego2" : 0,
		"Total_BB_Juego2" : 0,
		"Total_K_Juego2" : 0,
		"Total_Remolcadas_Juego2" : 3,
		"Total_Anotadas_Juego2" : 3,
		"Total_Innings_Lanzados" : 0.0,
		"Total_Ponches_Pitcher" : 0,
		"Total_BB_Pitcher" : 0
	},
	{
		"Numero" : 31,
		"Nombre_Completo" : "Luis Manuel Imanol",
		"Posicion" : "CF",
		"Total_Turnos_Juego1" : 120,
		"Total_H1_Juego1" : 6,
		"Total_H2_Juego1" : 12,
		"Total_H3_Juego1" : 6,
		"Total_H4_Juego1" : 12,
		"Total_BB_Juego1" : 12,
		"Total_K_Juego1" : 6,
		"Total_Remolcadas_Juego1" : 12,
		"Total_Anotadas_Juego1" : 12,
		"Total_Turnos_Juego2" : 91,
		"Total_H1_Juego2" : 14,
		"Total_H2_Juego2" : 14,
		"Total_H3_Juego2" : 0,
		"Total_H4_Juego2" : 14,
		"Total_BB_Juego2" : 7,
		"Total_K_Juego2" : 0,
		"Total_Remolcadas_Juego2" : 21,
		"Total_Anotadas_Juego2" : 21,
		"Total_Innings_Lanzados" : 0.0,
		"Total_Ponches_Pitcher" : 0,
		"Total_BB_Pitcher" : 0
	},
	{
		"Numero" : 44,
		"Nombre_Completo" : "Jean Carlos Ramos",
		"Posicion" : "RF",
		"Total_Turnos_Juego1" : 18,
		"Total_H1_Juego1" : 3,
		"Total_H2_Juego1" : 3,
		"Total_H3_Juego1" : 0,
		"Total_H4_Juego1" : 0,
		"Total_BB_Juego1" : 0,
		"Total_K_Juego1" : 0,
		"Total_Remolcadas_Juego1" : 0,
		"Total_Anotadas_Juego1" : 0,
		"Total_Turnos_Juego2" : 15,
		"Total_H1_Juego2" : 0,
		"Total_H2_Juego2" : 3,
		"Total_H3_Juego2" : 0,
		"Total_H4_Juego2" : 3,
		"Total_BB_Juego2" : 0,
		"Total_K_Juego2" : 0,
		"Total_Remolcadas_Juego2" : 0,
		"Total_Anotadas_Juego2" : 0,
		"Total_Innings_Lanzados" : 0.0,
		"Total_Ponches_Pitcher" : 0,
		"Total_BB_Pitcher" : 0
	},
	{
		"Numero" : 45,
		"Nombre_Completo" : "ABRAHAN",
		"Posicion" : "RF",
		"Total_Turnos_Juego1" : 52,
		"Total_H1_Juego1" : 4,
		"Total_H2_Juego1" : 4,
		"Total_H3_Juego1" : 4,
		"Total_H4_Juego1" : 0,
		"Total_BB_Juego1" : 12,
		"Total_K_Juego1" : 4,
		"Total_Remolcadas_Juego1" : 8,
		"Total_Anotadas_Juego1" : 4,
		"Total_Turnos_Juego2" : 40,
		"Total_H1_Juego2" : 10,
		"Total_H2_Juego2" : 5,
		"Total_H3_Juego2" : 5,
		"Total_H4_Juego2" : 5,
		"Total_BB_Juego2" : 0,
		"Total_K_Juego2" : 0,
		"Total_Remolcadas_Juego2" : 10,
		"Total_Anotadas_Juego2" : 0,
		"Total_Innings_Lanzados" : 0.0,
		"Total_Ponches_Pitcher" : 0,
		"Total_BB_Pitcher" : 0
	},
	{
		"Numero" : 46,
		"Nombre_Completo" : "DARWIN SANCHEZ",
		"Posicion" : "RF",
		"Total_Turnos_Juego1" : 75,
		"Total_H1_Juego1" : 30,
		"Total_H2_Juego1" : 0,
		"Total_H3_Juego1" : 5,
		"Total_H4_Juego1" : 0,
		"Total_BB_Juego1" : 5,
		"Total_K_Juego1" : 5,
		"Total_Remolcadas_Juego1" : 5,
		"Total_Anotadas_Juego1" : 5,
		"Total_Turnos_Juego2" : 40,
		"Total_H1_Juego2" : 10,
		"Total_H2_Juego2" : 10,
		"Total_H3_Juego2" : 0,
		"Total_H4_Juego2" : 10,
		"Total_BB_Juego2" : 5,
		"Total_K_Juego2" : 0,
		"Total_Remolcadas_Juego2" : 15,
		"Total_Anotadas_Juego2" : 15,
		"Total_Innings_Lanzados" : 0.0,
		"Total_Ponches_Pitcher" : 0,
		"Total_BB_Pitcher" : 0
	}
]
